{
  "generatedAt": "2026-06-29T00:00:58.003Z",
  "provider": "alpha-vantage",
  "status": "available",
  "stale": false,
  "message": "",
  "symbols": {
    "NVDA": {
      "symbol": "NVDA",
      "status": "available",
      "price": 192.53,
      "change": -3.21,
      "changePercent": "-1.6399%",
      "changePercentValue": -1.6399,
      "volume": 179304147,
      "tradingDay": "2026-06-26",
      "fetchedAt": "2026-06-29T00:00:58.003Z"
    },
    "MSFT": {
      "symbol": "MSFT",
      "status": "available",
      "price": 372.97,
      "change": 20.14,
      "changePercent": "5.7081%",
      "changePercentValue": 5.7081,
      "volume": 186201631,
      "tradingDay": "2026-06-26",
      "fetchedAt": "2026-06-29T00:00:58.003Z"
    },
    "GOOGL": {
      "symbol": "GOOGL",
      "status": "available",
      "price": 337.39,
      "change": -6.32,
      "changePercent": "-1.8388%",
      "changePercentValue": -1.8388,
      "volume": 114706326,
      "tradingDay": "2026-06-26",
      "fetchedAt": "2026-06-29T00:00:58.003Z"
    },
    "META": {
      "symbol": "META",
      "status": "available",
      "price": 550.25,
      "change": 7.38,
      "changePercent": "1.3594%",
      "changePercentValue": 1.3594,
      "volume": 18867706,
      "tradingDay": "2026-06-26",
      "fetchedAt": "2026-06-29T00:00:58.003Z"
    },
    "AMZN": {
      "symbol": "AMZN",
      "status": "available",
      "price": 232.69,
      "change": 5.68,
      "changePercent": "2.5021%",
      "changePercentValue": 2.5021,
      "volume": 248372085,
      "tradingDay": "2026-06-26",
      "fetchedAt": "2026-06-29T00:00:58.003Z"
    },
    "AMD": {
      "symbol": "AMD",
      "status": "available",
      "price": 521.58,
      "change": -10.99,
      "changePercent": "-2.0636%",
      "changePercentValue": -2.0636,
      "volume": 52705137,
      "tradingDay": "2026-06-26",
      "fetchedAt": "2026-06-29T00:00:58.003Z"
    },
    "AVGO": {
      "symbol": "AVGO",
      "status": "available",
      "price": 365.02,
      "change": -13.89,
      "changePercent": "-3.6658%",
      "changePercentValue": -3.6658,
      "volume": 34839253,
      "tradingDay": "2026-06-26",
      "fetchedAt": "2026-06-29T00:00:58.003Z"
    },
    "TSLA": {
      "symbol": "TSLA",
      "status": "available",
      "price": 379.71,
      "change": 4.59,
      "changePercent": "1.2236%",
      "changePercentValue": 1.2236,
      "volume": 53434138,
      "tradingDay": "2026-06-26",
      "fetchedAt": "2026-06-29T00:00:58.003Z"
    },
    "QQQ": {
      "symbol": "QQQ",
      "status": "available",
      "price": 706.52,
      "change": -9.86,
      "changePercent": "-1.3764%",
      "changePercentValue": -1.3764,
      "volume": 47081821,
      "tradingDay": "2026-06-26",
      "fetchedAt": "2026-06-29T00:00:58.003Z"
    },
    "SPY": {
      "symbol": "SPY",
      "status": "available",
      "price": 728.99,
      "change": -5.31,
      "changePercent": "-0.7231%",
      "changePercentValue": -0.7231,
      "volume": 71033969,
      "tradingDay": "2026-06-26",
      "fetchedAt": "2026-06-29T00:00:58.003Z"
    },
    "SMH": {
      "symbol": "SMH",
      "status": "available",
      "price": 611.61,
      "change": -25.27,
      "changePercent": "-3.9678%",
      "changePercentValue": -3.9678,
      "volume": 12728345,
      "tradingDay": "2026-06-26",
      "fetchedAt": "2026-06-29T00:00:58.003Z"
    }
  },
  "topMovers": [
    {
      "symbol": "SDOT",
      "price": 21.45,
      "changeAmount": 15.27,
      "changePercent": "247.0874%",
      "changePercentValue": 247.0874,
      "volume": 43870847,
      "direction": "gainer"
    },
    {
      "symbol": "PCLA",
      "price": 6.97,
      "changeAmount": 3.85,
      "changePercent": "123.3974%",
      "changePercentValue": 123.3974,
      "volume": 7159132,
      "direction": "gainer"
    },
    {
      "symbol": "CMIIW",
      "price": 1.31,
      "changeAmount": 0.71,
      "changePercent": "118.3333%",
      "changePercentValue": 118.3333,
      "volume": 1659832,
      "direction": "gainer"
    },
    {
      "symbol": "IVF",
      "price": 2.45,
      "changeAmount": 1.21,
      "changePercent": "97.5806%",
      "changePercentValue": 97.5806,
      "volume": 113007063,
      "direction": "gainer"
    },
    {
      "symbol": "ASBPW",
      "price": 0.0305,
      "changeAmount": 0.0133,
      "changePercent": "77.3256%",
      "changePercentValue": 77.3256,
      "volume": 8424,
      "direction": "gainer"
    },
    {
      "symbol": "WSHP",
      "price": 8,
      "changeAmount": 3.29,
      "changePercent": "69.8514%",
      "changePercentValue": 69.8514,
      "volume": 8005260,
      "direction": "gainer"
    },
    {
      "symbol": "HUMAW",
      "price": 0.0098,
      "changeAmount": 0.0038,
      "changePercent": "63.3333%",
      "changePercentValue": 63.3333,
      "volume": 73081,
      "direction": "gainer"
    },
    {
      "symbol": "CRIS",
      "price": 0.321,
      "changeAmount": 0.1152,
      "changePercent": "55.9767%",
      "changePercentValue": 55.9767,
      "volume": 101065706,
      "direction": "gainer"
    },
    {
      "symbol": "INLF",
      "price": 0.0467,
      "changeAmount": 0.0167,
      "changePercent": "55.6667%",
      "changePercentValue": 55.6667,
      "volume": 2204488039,
      "direction": "gainer"
    },
    {
      "symbol": "DFSCW",
      "price": 0.0332,
      "changeAmount": 0.0117,
      "changePercent": "54.4186%",
      "changePercentValue": 54.4186,
      "volume": 8429,
      "direction": "gainer"
    },
    {
      "symbol": "SBCWW",
      "price": 0.32,
      "changeAmount": 0.11,
      "changePercent": "52.381%",
      "changePercentValue": 52.381,
      "volume": 11285,
      "direction": "gainer"
    },
    {
      "symbol": "MRNOW",
      "price": 0.015,
      "changeAmount": 0.0049,
      "changePercent": "48.5149%",
      "changePercentValue": 48.5149,
      "volume": 94047,
      "direction": "gainer"
    },
    {
      "symbol": "ILLR",
      "price": 4.46,
      "changeAmount": 1.41,
      "changePercent": "46.2295%",
      "changePercentValue": 46.2295,
      "volume": 83633117,
      "direction": "gainer"
    },
    {
      "symbol": "HSCSW",
      "price": 0.0744,
      "changeAmount": 0.0234,
      "changePercent": "45.8824%",
      "changePercentValue": 45.8824,
      "volume": 1003,
      "direction": "gainer"
    },
    {
      "symbol": "NOEMW",
      "price": 0.1562,
      "changeAmount": 0.0462,
      "changePercent": "42.0%",
      "changePercentValue": 42,
      "volume": 182957,
      "direction": "gainer"
    },
    {
      "symbol": "CSHRW",
      "price": 0.83,
      "changeAmount": 0.241,
      "changePercent": "40.9168%",
      "changePercentValue": 40.9168,
      "volume": 11923,
      "direction": "gainer"
    },
    {
      "symbol": "SES+",
      "price": 0.0479,
      "changeAmount": 0.0136,
      "changePercent": "39.6501%",
      "changePercentValue": 39.6501,
      "volume": 12238,
      "direction": "gainer"
    },
    {
      "symbol": "SKYAW",
      "price": 0.0323,
      "changeAmount": 0.009,
      "changePercent": "38.6266%",
      "changePercentValue": 38.6266,
      "volume": 32543,
      "direction": "gainer"
    },
    {
      "symbol": "LVWR",
      "price": 1.395,
      "changeAmount": 0.385,
      "changePercent": "38.1188%",
      "changePercentValue": 38.1188,
      "volume": 3693911,
      "direction": "gainer"
    },
    {
      "symbol": "SABSW",
      "price": 0.0138,
      "changeAmount": 0.0038,
      "changePercent": "38.0%",
      "changePercentValue": 38,
      "volume": 100,
      "direction": "gainer"
    },
    {
      "symbol": "PSIG",
      "price": 1.45,
      "changeAmount": -10.35,
      "changePercent": "-87.7119%",
      "changePercentValue": -87.7119,
      "volume": 17897173,
      "direction": "loser"
    },
    {
      "symbol": "TBLAW",
      "price": 0.0004,
      "changeAmount": -0.0026,
      "changePercent": "-86.6667%",
      "changePercentValue": -86.6667,
      "volume": 643111,
      "direction": "loser"
    },
    {
      "symbol": "GWH+",
      "price": 0.0062,
      "changeAmount": -0.0132,
      "changePercent": "-68.0412%",
      "changePercentValue": -68.0412,
      "volume": 405968,
      "direction": "loser"
    },
    {
      "symbol": "KWMWW",
      "price": 0.009,
      "changeAmount": -0.0154,
      "changePercent": "-63.1148%",
      "changePercentValue": -63.1148,
      "volume": 161173,
      "direction": "loser"
    },
    {
      "symbol": "ONX",
      "price": 10.935,
      "changeAmount": -9.9197,
      "changePercent": "-47.5658%",
      "changePercentValue": -47.5658,
      "volume": 443648,
      "direction": "loser"
    },
    {
      "symbol": "ONG",
      "price": 7.06,
      "changeAmount": -6.2669,
      "changePercent": "-47.0244%",
      "changePercentValue": -47.0244,
      "volume": 419771,
      "direction": "loser"
    },
    {
      "symbol": "OIOWW",
      "price": 0.0374,
      "changeAmount": -0.0326,
      "changePercent": "-46.5714%",
      "changePercentValue": -46.5714,
      "volume": 10,
      "direction": "loser"
    },
    {
      "symbol": "BNCWZ",
      "price": 0.0268,
      "changeAmount": -0.0232,
      "changePercent": "-46.4%",
      "changePercentValue": -46.4,
      "volume": 172164,
      "direction": "loser"
    },
    {
      "symbol": "RNWWW",
      "price": 0.0028,
      "changeAmount": -0.0019,
      "changePercent": "-40.4255%",
      "changePercentValue": -40.4255,
      "volume": 7635,
      "direction": "loser"
    },
    {
      "symbol": "CELZ",
      "price": 1.2,
      "changeAmount": -0.8,
      "changePercent": "-40.0%",
      "changePercentValue": -40,
      "volume": 529491,
      "direction": "loser"
    },
    {
      "symbol": "LICN",
      "price": 1.02,
      "changeAmount": -0.65,
      "changePercent": "-38.9222%",
      "changePercentValue": -38.9222,
      "volume": 15427297,
      "direction": "loser"
    },
    {
      "symbol": "ANGH",
      "price": 3.31,
      "changeAmount": -2.07,
      "changePercent": "-38.4758%",
      "changePercentValue": -38.4758,
      "volume": 148243,
      "direction": "loser"
    },
    {
      "symbol": "TVRD",
      "price": 1.5,
      "changeAmount": -0.86,
      "changePercent": "-36.4407%",
      "changePercentValue": -36.4407,
      "volume": 762842,
      "direction": "loser"
    },
    {
      "symbol": "QTEXW",
      "price": 0.0318,
      "changeAmount": -0.0181,
      "changePercent": "-36.2725%",
      "changePercentValue": -36.2725,
      "volume": 22902,
      "direction": "loser"
    },
    {
      "symbol": "BEX",
      "price": 42.51,
      "changeAmount": -23.91,
      "changePercent": "-35.9982%",
      "changePercentValue": -35.9982,
      "volume": 1827324,
      "direction": "loser"
    },
    {
      "symbol": "RQI^",
      "price": 0.012,
      "changeAmount": -0.0065,
      "changePercent": "-35.1351%",
      "changePercentValue": -35.1351,
      "volume": 2130142,
      "direction": "loser"
    },
    {
      "symbol": "BTCT",
      "price": 0.74,
      "changeAmount": -0.4,
      "changePercent": "-35.0877%",
      "changePercentValue": -35.0877,
      "volume": 1406401,
      "direction": "loser"
    },
    {
      "symbol": "EVGOW",
      "price": 0.0054,
      "changeAmount": -0.0029,
      "changePercent": "-34.9398%",
      "changePercentValue": -34.9398,
      "volume": 1217132,
      "direction": "loser"
    },
    {
      "symbol": "NIXXW",
      "price": 0.0124,
      "changeAmount": -0.0066,
      "changePercent": "-34.7368%",
      "changePercentValue": -34.7368,
      "volume": 25436,
      "direction": "loser"
    },
    {
      "symbol": "BEG",
      "price": 61.2538,
      "changeAmount": -32.3653,
      "changePercent": "-34.5713%",
      "changePercentValue": -34.5713,
      "volume": 266525,
      "direction": "loser"
    },
    {
      "symbol": "INLF",
      "price": 0.0467,
      "changeAmount": 0.0167,
      "changePercent": "55.6667%",
      "changePercentValue": 55.6667,
      "volume": 2204488039,
      "direction": "active"
    },
    {
      "symbol": "SOXS",
      "price": 4.24,
      "changeAmount": 0.61,
      "changePercent": "16.8044%",
      "changePercentValue": 16.8044,
      "volume": 674267921,
      "direction": "active"
    },
    {
      "symbol": "GDC",
      "price": 0.0119,
      "changeAmount": -0.0018,
      "changePercent": "-13.1387%",
      "changePercentValue": -13.1387,
      "volume": 473682340,
      "direction": "active"
    },
    {
      "symbol": "TZA",
      "price": 3.9,
      "changeAmount": 0.04,
      "changePercent": "1.0363%",
      "changePercentValue": 1.0363,
      "volume": 370995560,
      "direction": "active"
    },
    {
      "symbol": "RCT",
      "price": 0.3567,
      "changeAmount": 0.0738,
      "changePercent": "26.087%",
      "changePercentValue": 26.087,
      "volume": 265115799,
      "direction": "active"
    },
    {
      "symbol": "AAPL",
      "price": 283.78,
      "changeAmount": 8.63,
      "changePercent": "3.1365%",
      "changePercentValue": 3.1365,
      "volume": 255581305,
      "direction": "active"
    },
    {
      "symbol": "AMZN",
      "price": 232.69,
      "changeAmount": 5.68,
      "changePercent": "2.5021%",
      "changePercentValue": 2.5021,
      "volume": 241167287,
      "direction": "active"
    },
    {
      "symbol": "BITO",
      "price": 8.12,
      "changeAmount": 0.06,
      "changePercent": "0.7444%",
      "changePercentValue": 0.7444,
      "volume": 232527204,
      "direction": "active"
    },
    {
      "symbol": "MSFT",
      "price": 372.97,
      "changeAmount": 20.14,
      "changePercent": "5.7081%",
      "changePercentValue": 5.7081,
      "volume": 181043973,
      "direction": "active"
    },
    {
      "symbol": "OPEN",
      "price": 4.37,
      "changeAmount": 0.07,
      "changePercent": "1.6279%",
      "changePercentValue": 1.6279,
      "volume": 168034170,
      "direction": "active"
    },
    {
      "symbol": "CDE",
      "price": 16.04,
      "changeAmount": 0.05,
      "changePercent": "0.3127%",
      "changePercentValue": 0.3127,
      "volume": 165496321,
      "direction": "active"
    },
    {
      "symbol": "NVDA",
      "price": 192.53,
      "changeAmount": -3.21,
      "changePercent": "-1.6399%",
      "changePercentValue": -1.6399,
      "volume": 163817382,
      "direction": "active"
    },
    {
      "symbol": "AAL",
      "price": 17.87,
      "changeAmount": 0.3,
      "changePercent": "1.7075%",
      "changePercentValue": 1.7075,
      "volume": 160273082,
      "direction": "active"
    },
    {
      "symbol": "NOK",
      "price": 13,
      "changeAmount": -0.98,
      "changePercent": "-7.01%",
      "changePercentValue": -7.01,
      "volume": 142187803,
      "direction": "active"
    },
    {
      "symbol": "HKIT",
      "price": 0.284,
      "changeAmount": 0.0611,
      "changePercent": "27.4114%",
      "changePercentValue": 27.4114,
      "volume": 127079828,
      "direction": "active"
    },
    {
      "symbol": "SPCX",
      "price": 153.23,
      "changeAmount": 0.23,
      "changePercent": "0.1503%",
      "changePercentValue": 0.1503,
      "volume": 125242807,
      "direction": "active"
    },
    {
      "symbol": "ONDS",
      "price": 7.83,
      "changeAmount": 0.155,
      "changePercent": "2.0195%",
      "changePercentValue": 2.0195,
      "volume": 121639628,
      "direction": "active"
    },
    {
      "symbol": "KEEL",
      "price": 6.03,
      "changeAmount": 0.16,
      "changePercent": "2.7257%",
      "changePercentValue": 2.7257,
      "volume": 121012745,
      "direction": "active"
    },
    {
      "symbol": "IVF",
      "price": 2.45,
      "changeAmount": 1.21,
      "changePercent": "97.5806%",
      "changePercentValue": 97.5806,
      "volume": 113007063,
      "direction": "active"
    },
    {
      "symbol": "GOOGL",
      "price": 337.39,
      "changeAmount": -6.32,
      "changePercent": "-1.8388%",
      "changePercentValue": -1.8388,
      "volume": 110933953,
      "direction": "active"
    }
  ],
  "newsSentiment": {
    "NVDA": [
      {
        "symbol": "NVDA",
        "title": "SA Asks: What's the most attractive robotics stock right now? (TER:NASDAQ)",
        "url": "https://seekingalpha.com/news/4607906-sa-asks-whats-the-most-attractive-robotics-stock-right-now",
        "source": "Seeking Alpha",
        "timePublished": "20260628T204152",
        "summary": "Seeking Alpha analysts Nelson Alves and Michael Del Monte weigh in on the most attractive robotics stocks. Alves picks Teradyne (TER) due to its strong robotics portfolio and AI semiconductor testing business. Del Monte highlights Zebra Technologies (ZBRA) for its growth potential through partnerships and considers Symbotic (SYM) as an emerging opportunity.",
        "overallSentimentScore": 0.230076,
        "overallSentimentLabel": "Somewhat-Bullish"
      },
      {
        "symbol": "NVDA",
        "title": "1 Stock That's More Than Doubled in 3 Years, and 3 Reasons It Will Keep Soaring",
        "url": "https://www.theglobeandmail.com/investing/markets/stocks/F-N/pressreleases/3024786/1-stock-that-s-more-than-doubled-in-3-years-and-3-reasons-it-will-keep-soaring/",
        "source": "The Globe and Mail",
        "timePublished": "20260628T200745",
        "summary": "General Motors (GM) stock has more than doubled in the last three years, significantly outperforming the S&P 500. This strong performance is attributed to GM's aggressive share buyback strategy, the high-margin recurring revenue generated by its OnStar and Super Cruise software services, and its pathway to electric vehicle (EV) profitability within three to five years. These factors suggest that GM is well-positioned for continued growth and could maintain its market-beating performance.",
        "overallSentimentScore": 0.362698,
        "overallSentimentLabel": "Bullish"
      },
      {
        "symbol": "NVDA",
        "title": "Intel Corporation (INTC)’s Stock Has Surged but Needs an Engineering Revival",
        "url": "https://uk.finance.yahoo.com/news/intel-corporation-intc-stock-surged-184539609.html",
        "source": "Yahoo Finance UK",
        "timePublished": "20260628T184603",
        "summary": "Intel Corporation's stock has surged over 550% in the past year due to new chip partnerships and government support, but the company still faces significant manufacturing challenges. Despite increased investor interest and analyst upgrades, its Intel Foundry segment reported a substantial operational loss in Q1. While Intel is making progress in manufacturing and benefiting from AI demand, some analysts suggest other AI stocks might offer better upside potential with less risk.",
        "overallSentimentScore": 0.223401,
        "overallSentimentLabel": "Somewhat-Bullish"
      },
      {
        "symbol": "NVDA",
        "title": "1 Unstoppable Trend That Could Supercharge Ford Stock by 2030",
        "url": "https://www.theglobeandmail.com/investing/markets/stocks/F/pressreleases/3024001/1-unstoppable-trend-that-could-supercharge-ford-stock-by-2030/",
        "source": "The Globe and Mail",
        "timePublished": "20260628T173745",
        "summary": "Ford is pivoting its manufacturing focus from Electric Vehicles (EVs) to producing battery energy storage systems (BESS) for AI data centers, which are facing significant power shortages. This strategic shift involves repurposing existing EV infrastructure and is expected to provide a new, stable revenue stream for Ford, potentially leading to a higher valuation for the company's stock. The company aims to manufacture 20 GWh of energy storage capacity annually, with the first BESS systems shipping as soon as 2027.",
        "overallSentimentScore": 0.283418,
        "overallSentimentLabel": "Somewhat-Bullish"
      },
      {
        "symbol": "NVDA",
        "title": "Constellation Energy (CEG) and Walmart Announce Long-Term Nuclear Power Purchase Agreement",
        "url": "https://www.insidermonkey.com/blog/constellation-energy-ceg-and-walmart-announce-long-term-nuclear-power-purchase-agreement-1791060/",
        "source": "Insider Monkey",
        "timePublished": "20260628T165115",
        "summary": "Constellation Energy (CEG) and Walmart have signed a long-term agreement for emissions-free nuclear power from Constellation's Dresden Clean Energy Center in Illinois. This deal, involving 176 MW of wholesale supply and 30 MW of expanded capacity, facilitates Walmart's access to cleaner energy and supports local energy infrastructure, starting with two 15-year terms in 2029 and 2030. The new power will specifically support Walmart's upcoming high-tech perishable distribution center in Belvidere, Illinois.",
        "overallSentimentScore": 0.250932,
        "overallSentimentLabel": "Somewhat-Bullish"
      },
      {
        "symbol": "NVDA",
        "title": "Aggregate net profit up last year",
        "url": "https://www.taipeitimes.com/News/biz/archives/2026/06/29/2003859889",
        "source": "Taipei Times",
        "timePublished": "20260628T154021",
        "summary": "Taiwan's 5,000 largest companies achieved a record high in aggregate net profit last year, increasing over 11% to NT$5.77 trillion, driven by strong global demand for AI applications. Contract chipmaker TSMC led in both net profit (NT$1.72 trillion) and revenue (NT$3.78 trillion), followed by other major tech and financial firms. Despite this overall growth, 772 companies reported losses, and the average return on equity fell to a three-year low, indicating uneven corporate performance.",
        "overallSentimentScore": 0.777527,
        "overallSentimentLabel": "Bullish"
      },
      {
        "symbol": "NVDA",
        "title": "This Tiny AI Stock Is Up By 680% in a Year. Is It A Buy?",
        "url": "https://www.theglobeandmail.com/investing/markets/stocks/AVGO/pressreleases/3023683/this-tiny-ai-stock-is-up-by-680-in-a-year-is-it-a-buy/",
        "source": "The Globe and Mail",
        "timePublished": "20260628T151042",
        "summary": "Aehr Test Systems, a specialist in stress-testing semiconductors for AI chips, has seen its stock rally by 680% in the past year, with over half of that gain in 2026 alone. The company is gaining significant traction with hyperscalers, securing substantial orders that could dramatically increase revenue, despite a high price-to-sales ratio and volatility. While its EV-related revenue declined, its focus on AI and data centers positions it for potential growth, making it an interesting, albeit risky, prospect for investors.",
        "overallSentimentScore": 0.334123,
        "overallSentimentLabel": "Somewhat-Bullish"
      },
      {
        "symbol": "NVDA",
        "title": "Penguin Solutions (PENG) Becomes NVIDIA AI Factory Specialized Partner",
        "url": "https://sg.finance.yahoo.com/news/penguin-solutions-peng-becomes-nvidia-081832928.html",
        "source": "Yahoo Finance Singapore",
        "timePublished": "20260628T151009",
        "summary": "Penguin Solutions Inc. (NASDAQ: PENG) has been designated an NVIDIA AI Factory Specialized Partner, marking a significant milestone in its decade-long collaboration with NVIDIA. This specialized status validates Penguin's robust capabilities in designing, deploying, and operating full-stack AI factories at scale, crucial for meeting accelerating demand in competitive industries. The company's proprietary platform integrates innovative offerings like OriginAI and ClusterWareAI, streamlining AI adoption for various end users.",
        "overallSentimentScore": 0.417989,
        "overallSentimentLabel": "Bullish"
      }
    ],
    "MSFT": [
      {
        "symbol": "MSFT",
        "title": "Constellation Energy (CEG) and Walmart Announce Long-Term Nuclear Power Purchase Agreement",
        "url": "https://www.insidermonkey.com/blog/constellation-energy-ceg-and-walmart-announce-long-term-nuclear-power-purchase-agreement-1791060/",
        "source": "Insider Monkey",
        "timePublished": "20260628T165115",
        "summary": "Constellation Energy (CEG) and Walmart have signed a long-term agreement for emissions-free nuclear power from Constellation's Dresden Clean Energy Center in Illinois. This deal, involving 176 MW of wholesale supply and 30 MW of expanded capacity, facilitates Walmart's access to cleaner energy and supports local energy infrastructure, starting with two 15-year terms in 2029 and 2030. The new power will specifically support Walmart's upcoming high-tech perishable distribution center in Belvidere, Illinois.",
        "overallSentimentScore": 0.250932,
        "overallSentimentLabel": "Somewhat-Bullish"
      },
      {
        "symbol": "MSFT",
        "title": "This Tiny AI Stock Is Up By 680% in a Year. Is It A Buy?",
        "url": "https://www.theglobeandmail.com/investing/markets/stocks/AVGO/pressreleases/3023683/this-tiny-ai-stock-is-up-by-680-in-a-year-is-it-a-buy/",
        "source": "The Globe and Mail",
        "timePublished": "20260628T151042",
        "summary": "Aehr Test Systems, a specialist in stress-testing semiconductors for AI chips, has seen its stock rally by 680% in the past year, with over half of that gain in 2026 alone. The company is gaining significant traction with hyperscalers, securing substantial orders that could dramatically increase revenue, despite a high price-to-sales ratio and volatility. While its EV-related revenue declined, its focus on AI and data centers positions it for potential growth, making it an interesting, albeit risky, prospect for investors.",
        "overallSentimentScore": 0.334123,
        "overallSentimentLabel": "Somewhat-Bullish"
      },
      {
        "symbol": "MSFT",
        "title": "Vanguard VT Challenges State Street NZAC in Global ETF Comparison",
        "url": "https://www.harianbasis.co/en/vanguard-vt-state-street-nzac-etf-comparison",
        "source": "HarianBasis.co",
        "timePublished": "20260628T124037",
        "summary": "This article compares two global ETFs: Vanguard Total World Stock ETF (VT) and State Street SPDR MSCI ACWI Climate Paris Aligned ETF (NZAC). VT offers broad global exposure at a lower cost and wider diversification, while NZAC prioritizes climate-related risk mitigation with a slightly higher expense ratio but also a higher dividend yield. The choice between them depends on an investor's goals regarding diversification versus climate-focused investing.",
        "overallSentimentScore": 0.100345,
        "overallSentimentLabel": "Neutral"
      },
      {
        "symbol": "MSFT",
        "title": "Oracle Eliminates 21,000 Jobs As Tech Giant Replaces 13% of Global Workforce With AI",
        "url": "https://www.tikr.com/blog/oracle-nyse-orcl-stock-eliminates-21000-jobs-as-tech-giant-replaces-13-of-global-workforce-with-ai",
        "source": "TIKR.com",
        "timePublished": "20260628T114825",
        "summary": "Oracle (ORCL) recently cut 21,000 jobs, or 13% of its global workforce, over the past year, attributing these reductions to the adoption and deployment of AI technologies. Despite significant spending on severance and massive capital expenditure for AI infrastructure, the company reported strong Q4 revenue growth of 21% year-over-year, with cloud infrastructure revenue surging by 93%. This situation highlights a conflict between Oracle's booming business driven by AI demand and the substantial costs and workforce restructuring involved in funding this growth.",
        "overallSentimentScore": -0.197398,
        "overallSentimentLabel": "Somewhat-Bearish"
      },
      {
        "symbol": "MSFT",
        "title": "JFrog (FROG) Is Up 5.9% After Bullish Analyst Views On AI And Cloud Security Tools",
        "url": "https://simplywall.st/stocks/us/software/nasdaq-frog/jfrog/news/jfrog-frog-is-up-59-after-bullish-analyst-views-on-ai-and-cl",
        "source": "Simply Wall Street",
        "timePublished": "20260628T111011",
        "summary": "JFrog (FROG) saw a 5.9% stock increase following positive analyst commentary on its AI-focused tools and cloud security offerings. Analysts highlighted JFrog's role in managing AI development workflows and securing cloud-native pipelines as key drivers of demand, reinforcing AI and security as central catalysts. Despite this optimism, the article warns investors to consider competitive threats in the security market that could impact pricing power and valuation.",
        "overallSentimentScore": 0.31819,
        "overallSentimentLabel": "Somewhat-Bullish"
      },
      {
        "symbol": "MSFT",
        "title": "Alphabet C background on Class C structure, shares shaped by long term strategy",
        "url": "https://www.ad-hoc-news.de/boerse/news/ueberblick/alphabet-c-background-on-class-c-structure-shares-shaped-by-long-term/69646523",
        "source": "Ad-hoc-news.de",
        "timePublished": "20260628T110749",
        "summary": "This article explains the background and structure of Alphabet Inc.'s Class C shares (GOOG), highlighting their non-voting status while fully participating in the company's economic performance. It details how this dual-class structure, introduced in 2014, preserves founder control and is a common arrangement among large U.S. technology companies. The article also covers Alphabet's core businesses, governance model, and where Class C shares are traded.",
        "overallSentimentScore": 0.175929,
        "overallSentimentLabel": "Somewhat-Bullish"
      },
      {
        "symbol": "MSFT",
        "title": "Wesbanco Bank Inc. Sells 35,099 Shares of Chevron Corporation $CVX",
        "url": "https://www.marketbeat.com/instant-alerts/filing-wesbanco-bank-inc-sells-35099-shares-of-chevron-corporation-cvx-2026-06-28/",
        "source": "MarketBeat",
        "timePublished": "20260628T104049",
        "summary": "Wesbanco Bank Inc. reduced its stake in Chevron Corporation (NYSE:CVX) by 12.8% in the first quarter of 2026, selling 35,099 shares and retaining 239,956 shares valued at approximately $49.6 million. Despite this reduction, Chevron remains a significant holding for the firm, representing 1.4% of their portfolio. Wall Street analysts maintain a \"Moderate Buy\" rating for Chevron with an average price target of $205.70, following recent positive news including its earnings beat and strategic deals with Microsoft and expansion into Greece.",
        "overallSentimentScore": 0.222564,
        "overallSentimentLabel": "Somewhat-Bullish"
      },
      {
        "symbol": "MSFT",
        "title": "Microsoft Corporation (MSFT) Is A Top Richard Chilton AI Stock",
        "url": "https://www.insidermonkey.com/blog/microsoft-corporation-msft-is-a-top-richard-chilton-ai-stock-1790956/",
        "source": "Insider Monkey",
        "timePublished": "20260628T103618",
        "summary": "Microsoft Corporation (NASDAQ:MSFT) is identified as one of the best stocks to buy according to billionaire Richard Chilton, despite its shares being down 22% year-to-date. The company is making significant investments in AI and supercomputing data centers and securing partnerships, such as with ICON plc for enterprise software and Chevron for power procurement. While the company faces concerns over cloud infrastructure investment and slower legacy software growth, its long-term thesis is supported by strong network effects and an embedded ecosystem.",
        "overallSentimentScore": 0.130212,
        "overallSentimentLabel": "Neutral"
      }
    ],
    "GOOGL": [
      {
        "symbol": "GOOGL",
        "title": "Intel Corporation (INTC)’s Stock Has Surged but Needs an Engineering Revival",
        "url": "https://uk.finance.yahoo.com/news/intel-corporation-intc-stock-surged-184539609.html",
        "source": "Yahoo Finance UK",
        "timePublished": "20260628T184603",
        "summary": "Intel Corporation's stock has surged over 550% in the past year due to new chip partnerships and government support, but the company still faces significant manufacturing challenges. Despite increased investor interest and analyst upgrades, its Intel Foundry segment reported a substantial operational loss in Q1. While Intel is making progress in manufacturing and benefiting from AI demand, some analysts suggest other AI stocks might offer better upside potential with less risk.",
        "overallSentimentScore": 0.242932,
        "overallSentimentLabel": "Somewhat-Bullish"
      },
      {
        "symbol": "GOOGL",
        "title": "Constellation Energy (CEG) and Walmart Announce Long-Term Nuclear Power Purchase Agreement",
        "url": "https://www.insidermonkey.com/blog/constellation-energy-ceg-and-walmart-announce-long-term-nuclear-power-purchase-agreement-1791060/",
        "source": "Insider Monkey",
        "timePublished": "20260628T165115",
        "summary": "Constellation Energy (CEG) and Walmart have signed a long-term agreement for emissions-free nuclear power from Constellation's Dresden Clean Energy Center in Illinois. This deal, involving 176 MW of wholesale supply and 30 MW of expanded capacity, facilitates Walmart's access to cleaner energy and supports local energy infrastructure, starting with two 15-year terms in 2029 and 2030. The new power will specifically support Walmart's upcoming high-tech perishable distribution center in Belvidere, Illinois.",
        "overallSentimentScore": 0.237036,
        "overallSentimentLabel": "Somewhat-Bullish"
      },
      {
        "symbol": "GOOGL",
        "title": "Autonomous & Self Driving Vehicle News: Waymo, Innoviz, WeRide, Karma, Tesla & May Mobility",
        "url": "https://www.autoconnectedcar.com/2026/06/autonomous-self-driving-vehicle-news-waymo-innoviz-weride-karma-tesla-may-mobility/",
        "source": "AUTO Connected Car News",
        "timePublished": "20260628T154000",
        "summary": "This article provides an update on recent developments in the autonomous and self-driving vehicle industry, featuring companies like Waymo, Innoviz, WeRide, Karma, Tesla, and May Mobility. Key announcements include Waymo expanding its robotaxi services to Nashville and Germany, Innoviz securing a LiDAR supply deal with Mobileye, and partnerships for right-hand-drive robotaxi deployments. The report also covers legal and safety challenges, such as investigations into Tesla's ADAS role in fatal crashes and a class-action lawsuit against Rivian, alongside insights into consumer trust and market expansion efforts.",
        "overallSentimentScore": 0.012541,
        "overallSentimentLabel": "Neutral"
      },
      {
        "symbol": "GOOGL",
        "title": "Alphabet C background on Class C structure, shares shaped by long term strategy",
        "url": "https://www.ad-hoc-news.de/boerse/news/ueberblick/alphabet-c-background-on-class-c-structure-shares-shaped-by-long-term/69646523",
        "source": "Ad-hoc-news.de",
        "timePublished": "20260628T110749",
        "summary": "This article explains the background and structure of Alphabet Inc.'s Class C shares (GOOG), highlighting their non-voting status while fully participating in the company's economic performance. It details how this dual-class structure, introduced in 2014, preserves founder control and is a common arrangement among large U.S. technology companies. The article also covers Alphabet's core businesses, governance model, and where Class C shares are traded.",
        "overallSentimentScore": 0.184146,
        "overallSentimentLabel": "Somewhat-Bullish"
      },
      {
        "symbol": "GOOGL",
        "title": "Worth Asset Management LLC Cuts Holdings in Alphabet Inc. $GOOGL",
        "url": "https://www.marketbeat.com/instant-alerts/filing-worth-asset-management-llc-cuts-holdings-in-alphabet-inc-googl-2026-06-28/",
        "source": "MarketBeat",
        "timePublished": "20260628T102450",
        "summary": "Worth Asset Management LLC significantly reduced its stake in Alphabet Inc. (NASDAQ:GOOGL) by 55.7% in the first quarter, selling 4,877 shares and retaining 3,882 shares valued at $1.12 million. Despite this reduction by one investor, institutional ownership of Alphabet remains strong at 40.03%. Wall Street analysts maintain a \"Moderate Buy\" rating for the stock, with an average price target of $413.13, even as the stock recently traded down 1.8% to $337.39 amidst mixed sentiment regarding its AI strategy and advertising revenue.",
        "overallSentimentScore": 0.055296,
        "overallSentimentLabel": "Neutral"
      },
      {
        "symbol": "GOOGL",
        "title": "J. L. Bainbridge & Co. Inc. Boosts Holdings in Blackstone Inc. $BX",
        "url": "https://www.marketbeat.com/instant-alerts/filing-j-l-bainbridge-co-inc-boosts-holdings-in-blackstone-inc-bx-2026-06-28/",
        "source": "MarketBeat",
        "timePublished": "20260628T100613",
        "summary": "J. L. Bainbridge & Co. Inc. significantly increased its stake in Blackstone Inc. during the first quarter, purchasing an additional 133,383 shares, bringing its total to 313,105 shares valued at approximately $36 million. Institutional investors maintain a high ownership around 70%, with several other firms also initiating new positions. Despite some analyst target reductions, Blackstone holds a \"Moderate Buy\" consensus rating, and has seen notable insider buying activity in recent months.",
        "overallSentimentScore": 0.267344,
        "overallSentimentLabel": "Somewhat-Bullish"
      },
      {
        "symbol": "GOOGL",
        "title": "Sterling Capital Management LLC Has $7.30 Million Stock Holdings in United Rentals, Inc. $URI",
        "url": "https://www.marketbeat.com/instant-alerts/filing-sterling-capital-management-llc-has-730-million-stock-holdings-in-united-rentals-inc-uri-2026-06-28/",
        "source": "MarketBeat",
        "timePublished": "20260628T091519",
        "summary": "Sterling Capital Management LLC reduced its stake in United Rentals (NYSE:URI) by 19.9% in the first quarter, now holding 10,018 shares valued at approximately $7.3 million. Despite mixed quarterly results where revenue increased but EPS missed estimates, analysts maintain a \"Moderate Buy\" rating with an average price target of $1,070.50. Insider selling was noted, with the CEO and EVP selling shares worth a combined $25.6 million over the last 90 days.",
        "overallSentimentScore": 0.069718,
        "overallSentimentLabel": "Neutral"
      },
      {
        "symbol": "GOOGL",
        "title": "The AI Startup Challenging Tesla and Waymo in the Race to Automate Driving",
        "url": "https://www.wsj.com/business/autos/wayve-self-driving-technology-2e917ebd",
        "source": "WSJ",
        "timePublished": "20260628T090843",
        "summary": "Wayve, an autonomous vehicle startup, is leveraging its AI-powered driving system to compete with industry leaders like Waymo and Tesla. They recently demonstrated their technology on Jeep Grand Cherokees for Stellantis, resulting in a commitment to deploy the technology across America. This highlights Wayve's emergence as a key partner for traditional automakers aiming to integrate self-driving capabilities.",
        "overallSentimentScore": -0.052468,
        "overallSentimentLabel": "Neutral"
      }
    ]
  }
}
